MeshEditor/MeshEditor.py
MeshEditor/__init__.py
MeshEditor-0.6.4.dist-info/LICENCE.txt
MeshEditor-0.6.4.dist-info/METADATA
MeshEditor-0.6.4.dist-info/WHEEL
MeshEditor-0.6.4.dist-info/top_level.txt
MeshEditor-0.6.4.dist-info/RECORD
