Metadata-Version: 2.1
Name: MeshEditor
Version: 0.6.4
Summary: A package for editing and landmarking meshes
Author-email: Harold Matthews <harrymatthews50@gmail.com>
Project-URL: Homepage, https://github.com/harrymatthews50/MeshEditor
Classifier: Programming Language :: Python :: 3
Classifier: License :: OSI Approved :: MIT License
Classifier: Operating System :: OS Independent
Requires-Python: >=3.10
License-File: LICENCE.txt
Requires-Dist: pyvista (>=0.37)
Requires-Dist: scipy (>=1.3)
